ynab_unlinked/__about__.py
ynab_unlinked/__init__.py
ynab_unlinked/choices.py
ynab_unlinked/context_object.py
ynab_unlinked/display.py
ynab_unlinked/exceptions.py
ynab_unlinked/formatter.py
ynab_unlinked/main.py
ynab_unlinked/matcher.py
ynab_unlinked/models.py
ynab_unlinked/parsers.py
ynab_unlinked/payee.py
ynab_unlinked/process.py
ynab_unlinked/utils.py
ynab_unlinked/commands/__init__.py
ynab_unlinked/commands/config.py
ynab_unlinked/commands/load.py
ynab_unlinked/commands/reconcile.py
ynab_unlinked/commands/apps/__init__.py
ynab_unlinked/commands/apps/app.tcss
ynab_unlinked/commands/apps/reconcile.py
ynab_unlinked/config/__init__.py
ynab_unlinked/config/constants.py
ynab_unlinked/config/core.py
ynab_unlinked/config/paths.py
ynab_unlinked/config/types.py
ynab_unlinked/config/migrations/__init__.py
ynab_unlinked/config/migrations/base.py
ynab_unlinked/config/migrations/types.py
ynab_unlinked/config/models/__init__.py
ynab_unlinked/config/models/config_migrations.py
ynab_unlinked/config/models/shared.py
ynab_unlinked/config/models/v1.py
ynab_unlinked/config/models/v2.py
ynab_unlinked/entities/__init__.py
ynab_unlinked/entities/_protocol.py
ynab_unlinked/entities/bbva/__init__.py
ynab_unlinked/entities/bbva/bbva.py
ynab_unlinked/entities/bbva/command.py
ynab_unlinked/entities/cobee/__init__.py
ynab_unlinked/entities/cobee/cobee.py
ynab_unlinked/entities/cobee/command.py
ynab_unlinked/entities/sabadell/__init__.py
ynab_unlinked/entities/sabadell/command.py
ynab_unlinked/entities/sabadell/sabadell.py
ynab_unlinked/parsers/__init__.py
ynab_unlinked/parsers/pdf.py
ynab_unlinked/parsers/xls.py
ynab_unlinked/ynab_api/__init__.py
ynab_unlinked/ynab_api/client.py
ynab_unlinked-0.6.1.dist-info/METADATA
ynab_unlinked-0.6.1.dist-info/WHEEL
ynab_unlinked-0.6.1.dist-info/entry_points.txt
ynab_unlinked-0.6.1.dist-info/licenses/LICENSE.txt
ynab_unlinked-0.6.1.dist-info/RECORD
